<?xml version="1.0" encoding="utf-8" ?><dwsync><file name="accesories.html" server="www.bubbling-library.com//sandbox/" local="3310945440" remote="3310945440" /><file name="accesories.php" server="www.bubbling-library.com//sandbox/" local="3310945440" remote="3310945440" /><file name="photos.html" server="www.bubbling-library.com//sandbox/" local="3310945440" remote="3310945440" /><file name="photos.php" server="www.bubbling-library.com//sandbox/" local="3310945440" remote="3310945440" /><file name="tv.html" server="www.bubbling-library.com//sandbox/" local="3310945440" remote="3310945440" /><file name="tv.php" server="www.bubbling-library.com//sandbox/" local="3310945440" remote="3310945440" /><file name="view.html" server="www.bubbling-library.com//sandbox/" local="3310945440" remote="3310945440" /><file name="view.php" server="www.bubbling-library.com//sandbox/" local="3310945440" remote="3310945440" /></dwsync>